comperm/__init__.py
comperm/com_op.py
comperm/combinatorics_op.py
comperm/per_op.py
comperm-2022.6.0.dist-info/LICENSE.txt
comperm-2022.6.0.dist-info/METADATA
comperm-2022.6.0.dist-info/WHEEL
comperm-2022.6.0.dist-info/top_level.txt
comperm-2022.6.0.dist-info/RECORD
