Metadata-Version: 2.1
Name: comperm
Version: 2022.6.0
Summary: Combination and permutation operations.
Author-email: "谢方圆 (XIE Fangyuan)" <xie.fangyuan@foxmail.com>
License: MIT License
Project-URL: Homepage, https://gitee.com/xie-fangyuan/comperm
Keywords: combination,permutation
Classifier: Programming Language :: Python :: 3.10
Classifier: Operating System :: OS Independent
Classifier: License :: OSI Approved :: MIT License
Requires-Python: >=3.10
License-File: LICENSE.txt
